gabwill10_testing/core/index.py
gabwill10_testing-0.5.0.dist-info/WHEEL
gabwill10_testing-0.5.0.dist-info/METADATA
gabwill10_testing-0.5.0.dist-info/RECORD
