Metadata-Version: 2.1
Name: gabwill10-testing
Version: 0.5.0
Summary: first library
License: free
Author: Gabriel Gonzalez
Requires-Python: >=3.8,<4.0
Classifier: License :: Other/Proprietary License
Classifier: Programming Language :: Python :: 3
Classifier: Programming Language :: Python :: 3.10
Classifier: Programming Language :: Python :: 3.8
Classifier: Programming Language :: Python :: 3.9
Requires-Dist: flake8 (>=3.9.2,<4.0.0)
